{
	"hash": "d41d8cd98f00b204e9800998ecf8427e",
	"updated": "2020-11-30T07:07:12.4135539-03:00",
	"installedModules": {
		"https://github.com/carloshe/socialmonkey": {
			"name": "socialmonkey",
			"version": "0.0.5",
			"hash": "3207040192f27832e3ba689cd67d239d",
			"artifacts": {
				"dcp": [
					"SocialMonkeyPackage.dcp"
				],
				"dcu": [
					"SocialMonkey.AbstractSocialUser.dcu",
					"SocialMonkey.Components.BaseProvider.dcu",
					"SocialMonkey.Components.FacebookProvider.dcu",
					"SocialMonkey.Components.Manager.dcu",
					"SocialMonkey.Components.Reg.dcu",
					"SocialMonkey.Contracts.Factory.dcu",
					"SocialMonkey.Contracts.Provider.dcu",
					"SocialMonkey.Contracts.SocialUser.dcu",
					"SocialMonkey.Contracts.SocialWebBrowser.dcu",
					"SocialMonkey.Manager.dcu",
					"SocialMonkey.Providers.Contracts.FacebookProvider.dcu",
					"SocialMonkey.Providers.FacebookProvider.dcu",
					"SocialMonkey.SocialWebBrowser.dcu",
					"SocialMonkey.Two.AbstractProvider.dcu",
					"SocialMonkey.Two.ProviderInterface.dcu",
					"SocialMonkey.Two.SocialUser.dcu",
					"SocialMonkey.Types.dcu",
					"SocialMonkey.WebBrowserView.dcu"
				],
				"bpl": [
					"SocialMonkeyPackage.bpl"
				]
			},
			"failed": false,
			"changed": false
		}
	}
}